{"id": "ElliAl01", "header": {"name": "Alex Ellis", "position": "TE", "age": 28, "college": "Tennessee"}, "stats": [{"stat_type": "rush_rec", "table": [{"year": 2016, "age": 23, "uniform_number": 48, "g": 6, "gs": 3, "targets": 4, "rec": 3, "rec_yds": 11, "rec_yds_per_rec": 3.7, "rec_td": 0, "rec_first_down": 0, "rec_long": 6, "rec_per_g": 0.5, "rec_yds_per_g": 1.8, "catch_pct": 75.0, "rec_yds_per_tgt": 2.8, "rush_att": 0, "rush_yds": 0, "rush_td": 0, "rush_first_down": 0, "rush_long": 0, "rush_yds_per_att": 0.0, "rush_yds_per_g": 0.0, "rush_att_per_g": 0.0, "touches": 3, "yds_per_touch": 3.7, "yds_from_scrimmage": 11, "rush_receive_td": 0, "fumbles": 0, "av": 0}, {"year": 2018, "age": 25, "uniform_number": 82, "g": 2, "gs": 0, "targets": 0, "rec": 0, "rec_yds": 0, "rec_yds_per_rec": 0.0, "rec_td": 0, "rec_first_down": 0, "rec_long": 0, "rec_per_g": 0.0, "rec_yds_per_g": 0.0, "catch_pct": 0.0, "rec_yds_per_tgt": 0.0, "rush_att": 0, "rush_yds": 0, "rush_td": 0, "rush_first_down": 0, "rush_long": 0, "rush_yds_per_att": 0.0, "rush_yds_per_g": 0.0, "rush_att_per_g": 0.0, "touches": 0, "yds_per_touch": 0.0, "yds_from_scrimmage": 0, "rush_receive_td": 0, "fumbles": 0, "av": 0}, {"year": 2019, "age": 26, "uniform_number": 85, "g": 3, "gs": 0, "targets": 0, "rec": 0, "rec_yds": 0, "rec_yds_per_rec": 0.0, "rec_td": 0, "rec_first_down": 0, "rec_long": 0, "rec_per_g": 0.0, "rec_yds_per_g": 0.0, "catch_pct": 0.0, "rec_yds_per_tgt": 0.0, "rush_att": 0, "rush_yds": 0, "rush_td": 0, "rush_first_down": 0, "rush_long": 0, "rush_yds_per_att": 0.0, "rush_yds_per_g": 0.0, "rush_att_per_g": 0.0, "touches": 0, "yds_per_touch": 0.0, "yds_from_scrimmage": 0, "rush_receive_td": 0, "fumbles": 0, "av": 0}]}, {"stat_type": "defense", "table": [{"year": 2016, "age": 23, "uniform_number": 48, "g": 6, "gs": 3, "def_int": 0, "def_int_yds": 0, "def_int_td": 0, "def_int_long": 0, "pass_defended": 0, "fumbles_forced": 0, "fumbles": 0, "fumbles_rec": 0, "fumbles_rec_yds": 0, "fumbles_rec_td": 0, "sacks": 0.0, "tackles_combined": 1, "tackles_solo": 1, "tackles_assists": 0, "tackles_loss": 0, "qb_hits": 0, "safety_md": 0}]}]}