{"id": "BrowAJ00", "header": {"name": "A.J. Brown", "position": "WR", "team": "TEN", "age": 23, "college": "Mississippi"}, "stats": [{"stat_type": "rush_rec", "table": [{"year": 2019, "age": 22, "uniform_number": 11, "g": 16, "gs": 11, "targets": 84, "rec": 52, "rec_yds": 1051, "rec_yds_per_rec": 20.2, "rec_td": 8, "rec_first_down": 39, "rec_long": 91, "rec_per_g": 3.3, "rec_yds_per_g": 65.7, "catch_pct": 61.9, "rec_yds_per_tgt": 12.5, "rush_att": 3, "rush_yds": 60, "rush_td": 1, "rush_first_down": 2, "rush_long": 49, "rush_yds_per_att": 20.0, "rush_yds_per_g": 3.8, "rush_att_per_g": 0.2, "touches": 55, "yds_per_touch": 20.2, "yds_from_scrimmage": 1111, "rush_receive_td": 9, "fumbles": 1, "av": 10}, {"year": 2020, "age": 23, "uniform_number": 11, "g": 14, "gs": 12, "targets": 106, "rec": 70, "rec_yds": 1075, "rec_yds_per_rec": 15.4, "rec_td": 11, "rec_first_down": 55, "rec_long": 73, "rec_per_g": 5.0, "rec_yds_per_g": 76.8, "catch_pct": 66.0, "rec_yds_per_tgt": 10.1, "rush_att": 0, "rush_yds": 0, "rush_td": 0, "rush_first_down": 0, "rush_long": 0, "rush_yds_per_att": 0.0, "rush_yds_per_g": 0.0, "rush_att_per_g": 0.0, "touches": 70, "yds_per_touch": 15.4, "yds_from_scrimmage": 1075, "rush_receive_td": 11, "fumbles": 2, "av": 13}]}, {"stat_type": "adv_rush_rec", "table": [{"year": 2019, "age": 22, "uniform_number": 11, "g": 16, "gs": 11, "targets": 84, "rec": 52, "rec_yds": 1051, "rec_first_down": 39, "rec_air_yds": 586, "rec_air_yds_per_rec": 11.3, "rec_yac": 465, "rec_yac_per_rec": 8.9, "rec_adot": 13.2, "rec_broken_tackles": 8, "rec_broken_tackles_per_rec": 6.5, "rec_drops": 2, "rec_drop_pct": 2.4, "rec_target_int": 2, "rec_pass_rating": 127.6, "rush_att": 3, "rush_yds": 60, "rush_first_down": 2, "rush_yds_before_contact": 12, "rush_yds_bc_per_rush": 4.0, "rush_yac": 48, "rush_yac_per_rush": 16.0, "rush_broken_tackles": 1, "rush_broken_tackles_per_rush": 3.0}, {"year": 2020, "age": 23, "uniform_number": 11, "g": 14, "gs": 12, "targets": 106, "rec": 70, "rec_yds": 1075, "rec_first_down": 55, "rec_air_yds": 643, "rec_air_yds_per_rec": 9.2, "rec_yac": 432, "rec_yac_per_rec": 6.2, "rec_adot": 10.9, "rec_broken_tackles": 13, "rec_broken_tackles_per_rec": 5.4, "rec_drops": 5, "rec_drop_pct": 4.7, "rec_target_int": 2, "rec_pass_rating": 126.1, "rush_att": 0, "rush_yds": 0, "rush_first_down": 0, "rush_yds_before_contact": 0, "rush_yds_bc_per_rush": 0.0, "rush_yac": 0, "rush_yac_per_rush": 0.0, "rush_broken_tackles": 0, "rush_broken_tackles_per_rush": 0.0}]}, {"stat_type": "returns", "table": [{"year": 2020, "age": 23, "uniform_number": 11, "g": 14, "gs": 12, "punt_ret": 0, "punt_ret_yds": 0, "punt_ret_td": 0, "punt_ret_long": 0, "punt_ret_yds_per_ret": 0.0, "kick_ret": 1, "kick_ret_yds": 42, "kick_ret_td": 0, "kick_ret_long": 42, "kick_ret_yds_per_ret": 42.0, "all_purpose_yds": 1117}]}]}